{
  "channels": [
    {
      "position": 0,
      "name": "",
      "url": ""
    },
    {
      "position": 1,
      "name": "",
      "url": ""
    },
    {
      "position": 2,
      "name": "",
      "url": ""
    },
    {
      "position": 3,
      "name": "",
      "url": ""
    },
    {
      "position": 4,
      "name": "",
      "url": ""
    },
    {
      "position": 5,
      "name": "",
      "url": ""
    },
    {
      "position": 6,
      "name": "",
      "url": ""
    },
    {
      "position": 7,
      "name": "",
      "url": ""
    },
    {
      "position": 8,
      "name": "",
      "url": ""
    },
    {
      "position": 9,
      "name": "",
      "url": ""
    },
    {
      "position": 10,
      "name": "",
      "url": ""
    }
  ]
}